botmaker/__init__.py
botmaker/client.py
botmaker/exc.py
botmaker/helpers.py
botmaker/version.py
botmaker/resources/__init__.py
botmaker/resources/base.py
botmaker/resources/messages.py
botmaker/resources/template_messages.py
tests/__init__.py
tests/conftest.py
tests/test_auth.py
tests/test_client.py
tests/test_exc.py
tests/test_helpers.py
tests/test_messages.py
tests/test_template_messages.py
tests/test_whatsapp.py
botmaker-0.3.5.dist-info/LICENSE
botmaker-0.3.5.dist-info/METADATA
botmaker-0.3.5.dist-info/WHEEL
botmaker-0.3.5.dist-info/top_level.txt
botmaker-0.3.5.dist-info/RECORD
