Metadata-Version: 2.1
Name: botmaker
Version: 0.3.5
Summary: BotMaker API Client
Home-page: https://github.com/cuenca-mx/botmaker-python
Author: Cuenca
Author-email: dev@cuenca.com
License: UNKNOWN
Platform: UNKNOWN
Classifier: Programming Language :: Python :: 3
Classifier: Programming Language :: Python :: 3.6
Classifier: Programming Language :: Python :: 3.7
Classifier: License :: OSI Approved :: MIT License
Classifier: Operating System :: OS Independent
Requires-Python: >=3.6
Requires-Dist: requests (<3.0.0,>=2.21.0)
Requires-Dist: dataclasses (>=0.6) ; python_version < "3.7"
Provides-Extra: test
Requires-Dist: pytest ; extra == 'test'
Requires-Dist: pytest-vcr ; extra == 'test'
Requires-Dist: pytest-cov ; extra == 'test'
Requires-Dist: black ; extra == 'test'
Requires-Dist: isort ; extra == 'test'
Requires-Dist: flake8 (==3.7.9) ; extra == 'test'
Requires-Dist: mypy (==0.812) ; extra == 'test'
